{"is_source_file": false, "format": null, "description": null, "external_files": [], "external_methods": [], "published": [], "classes": [], "methods": [], "calls": [], "search-terms": [], "state": 2, "file_id": 26, "knowledge_revision": 60, "git_revision": "", "hash": "4bd9f56d67e63b044f59166d9c9eef5f", "format-version": 4, "code-base-name": "ai_models_web_app_frontend", "filename": "ai_models_web_app_frontend/src/app/models/image-captioner/image-captioner.component.html", "revision_history": [{"60": ""}]}